pytest_django_testing_postgresql.py
pytest_django_testing_postgresql-0.2.dist-info/LICENSE
pytest_django_testing_postgresql-0.2.dist-info/METADATA
pytest_django_testing_postgresql-0.2.dist-info/WHEEL
pytest_django_testing_postgresql-0.2.dist-info/entry_points.txt
pytest_django_testing_postgresql-0.2.dist-info/top_level.txt
pytest_django_testing_postgresql-0.2.dist-info/RECORD
