Metadata-Version: 2.1
Name: pytest-django-testing-postgresql
Version: 0.2
Summary: Use a temporary PostgreSQL database with pytest-django
Home-page: https://edugit.org/AlekSIS/libs/pytest-django-testing-postgresql
Author: Dominik George
Author-email: nik@naturalnet.de
License: UNKNOWN
Platform: UNKNOWN
Classifier: Development Status :: 4 - Beta
Classifier: Framework :: Django
Classifier: Framework :: Pytest
Classifier: Intended Audience :: Developers
Classifier: License :: OSI Approved :: Apache Software License
Classifier: Programming Language :: Python :: 3
License-File: LICENSE
Requires-Dist: dj-database-url
Requires-Dist: testing.postgresql
